h5tab.py
h5tab-1.0.1.dist-info/licenses/LICENSE.md
h5tab-1.0.1.dist-info/METADATA
h5tab-1.0.1.dist-info/WHEEL
h5tab-1.0.1.dist-info/entry_points.txt
h5tab-1.0.1.dist-info/top_level.txt
h5tab-1.0.1.dist-info/RECORD
