Metadata-Version: 2.4
Name: h5tab
Version: 1.0.1
Summary: Simple HDF5 file viewer.
Author-email: John Helly <j.c.helly@durham.ac.uk>
Project-URL: Homepage, https://github.com/jchelly/h5tab
Project-URL: Repository, https://github.com/jchelly/h5tab.git
Project-URL: Issues, https://github.com/jchelly/h5tab/issues
Classifier: Programming Language :: Python :: 3
Classifier: License :: OSI Approved :: GNU General Public License v3 (GPLv3)
Classifier: Operating System :: OS Independent
Requires-Python: >=3.7
License-File: LICENSE.md
Requires-Dist: h5py
Dynamic: license-file
